<?xml version="1.0" encoding="UTF-8"?>
<!-- Generated by Fujitsu Interstage XWand B0255 -->
<link:linkbase xmlns:xsi="http://www.w3.org/2001/XMLSchema-instance" xsi:schemaLocation="http://www.xbrl.org/2003/linkbase http://www.xbrl.org/2003/xbrl-linkbase-2003-12-31.xsd" xmlns:link="http://www.xbrl.org/2003/linkbase" xmlns:xbrldt="http://xbrl.org/2005/xbrldt" xmlns:xlink="http://www.w3.org/1999/xlink" xmlns:xbrli="http://www.xbrl.org/2003/instance">
  <link:roleRef roleURI="http://www.cbr.ru/xbrl/nso/ins/rep/2025-12-30/tab/sr_0420152/sr_0420152_MeneeOdinProts/1" xlink:type="simple" xlink:href="sr_0420152.xsd#sr_0420152_MeneeOdinProts_1"/>
  <link:roleRef roleURI="http://www.cbr.ru/xbrl/nso/ins/rep/2025-12-30/tab/sr_0420152/sr_0420152_MeneeOdinProts/2" xlink:type="simple" xlink:href="sr_0420152.xsd#sr_0420152_MeneeOdinProts_2"/>
  <link:roleRef roleURI="http://www.cbr.ru/xbrl/nso/ins/rep/2025-12-30/tab/sr_0420152/sr_0420152_R1/1" xlink:type="simple" xlink:href="sr_0420152.xsd#sr_0420152_R1_hc1"/>
  <link:roleRef roleURI="http://www.cbr.ru/xbrl/nso/ins/rep/2025-12-30/tab/sr_0420152/sr_0420152_R1Spr" xlink:type="simple" xlink:href="sr_0420152.xsd#sr_0420152_R1Spr"/>
  <link:presentationLink xlink:type="extended" xlink:role="http://www.cbr.ru/xbrl/nso/ins/rep/2025-12-30/tab/sr_0420152/sr_0420152_MeneeOdinProts/1">
    <link:loc xlink:type="locator" xlink:href="../../../../dic/ins-dic.xsd#ins-dic_Sluzhebnyi_Abstract" xlink:label="Sluzhebnyi_Abstract" xlink:title="Sluzhebnyi_Abstract"/>
    <link:loc xlink:type="locator" xlink:href="http://www.eurofiling.info/eu/fr/xbrl/ext/model.xsd#hyp" xlink:label="hyp" xlink:title="hyp"/>
    <link:presentationArc xlink:type="arc" xlink:arcrole="http://www.xbrl.org/2003/arcrole/parent-child" xlink:from="Sluzhebnyi_Abstract" xlink:to="hyp" xlink:title="presentation: Sluzhebnyi_Abstract to hyp" order="1.0" xbrldt:contextElement="scenario" xbrldt:closed="true"/>
    <link:loc xlink:type="locator" xlink:href="../../../../../../udr/dim/dim-int.xsd#dim-int_Tip_Akczionerov_Axis" xlink:label="Tip_Akczionerov_Axis" xlink:title="Tip_Akczionerov_Axis"/>
    <link:presentationArc xlink:type="arc" xlink:arcrole="http://www.xbrl.org/2003/arcrole/parent-child" xlink:from="hyp" xlink:to="Tip_Akczionerov_Axis" xlink:title="presentation: hyp to Tip_Akczionerov_Axis" order="1.0"/>
    <link:loc xlink:type="locator" xlink:href="../../../../../../udr/dom/mem-int.xsd#mem-int_Rezidenty_YulMember" xlink:label="Rezidenty_YulMember" xlink:title="Rezidenty_YulMember"/>
    <link:presentationArc xlink:type="arc" xlink:arcrole="http://www.xbrl.org/2003/arcrole/parent-child" xlink:from="Tip_Akczionerov_Axis" xlink:to="Rezidenty_YulMember" xlink:title="presentation: Tip_Akczionerov_Axis to Rezidenty_YulMember" order="1.0"/>
    <link:loc xlink:type="locator" xlink:href="../../../../../../udr/dim/dim-int.xsd#dim-int_Tip_KontragentaAxis" xlink:label="Tip_KontragentaAxis" xlink:title="Tip_KontragentaAxis"/>
    <link:presentationArc xlink:type="arc" xlink:arcrole="http://www.xbrl.org/2003/arcrole/parent-child" xlink:from="hyp" xlink:to="Tip_KontragentaAxis" xlink:title="presentation: hyp to Tip_KontragentaAxis" order="2.0"/>
    <link:loc xlink:type="locator" xlink:href="../../../../../../udr/dom/mem-int.xsd#mem-int_AkczUchSovDolyaUkMeneeOdProtsMember" xlink:label="AkczUchSovDolyaUkMeneeOdProtsMember" xlink:title="AkczUchSovDolyaUkMeneeOdProtsMember"/>
    <link:presentationArc xlink:type="arc" xlink:arcrole="http://www.xbrl.org/2003/arcrole/parent-child" xlink:from="Tip_KontragentaAxis" xlink:to="AkczUchSovDolyaUkMeneeOdProtsMember" xlink:title="presentation: Tip_KontragentaAxis to AkczUchSovDolyaUkMeneeOdProtsMember" order="1.0"/>
    <link:loc xlink:type="locator" xlink:href="../../../../dic/ins-dic.xsd#ins-dic_Summa_Doli_Akczionerov_V_Uk" xlink:label="Summa_Doli_Akczionerov_V_Uk" xlink:title="Summa_Doli_Akczionerov_V_Uk"/>
    <link:presentationArc xlink:type="arc" xlink:arcrole="http://www.xbrl.org/2003/arcrole/parent-child" xlink:from="Sluzhebnyi_Abstract" xlink:to="Summa_Doli_Akczionerov_V_Uk" xlink:title="presentation: Sluzhebnyi_Abstract to Summa_Doli_Akczionerov_V_Uk" order="2.0" preferredLabel="http://www.xbrl.org/2003/role/periodStartLabel"/>
    <link:loc xlink:type="locator" xlink:href="../../../../dic/ins-dic.xsd#ins-dic_Summa_Doli_Akczionerov_V_Uk" xlink:label="Summa_Doli_Akczionerov_V_Uk_2" xlink:title="Summa_Doli_Akczionerov_V_Uk"/>
    <link:presentationArc xlink:type="arc" xlink:arcrole="http://www.xbrl.org/2003/arcrole/parent-child" xlink:from="Sluzhebnyi_Abstract" xlink:to="Summa_Doli_Akczionerov_V_Uk_2" xlink:title="presentation: Sluzhebnyi_Abstract to Summa_Doli_Akczionerov_V_Uk" order="5.0" preferredLabel="http://www.xbrl.org/2003/role/periodEndLabel"/>
    <link:loc xlink:type="locator" xlink:href="../../../../dic/ins-dic.xsd#ins-dic_Procent_Doli_Akczionerov_V_Uk" xlink:label="Procent_Doli_Akczionerov_V_Uk" xlink:title="Procent_Doli_Akczionerov_V_Uk"/>
    <link:presentationArc xlink:type="arc" xlink:arcrole="http://www.xbrl.org/2003/arcrole/parent-child" xlink:from="Sluzhebnyi_Abstract" xlink:to="Procent_Doli_Akczionerov_V_Uk" xlink:title="presentation: Sluzhebnyi_Abstract to Procent_Doli_Akczionerov_V_Uk" order="3.0" preferredLabel="http://www.xbrl.org/2003/role/periodStartLabel"/>
    <link:loc xlink:type="locator" xlink:href="../../../../dic/ins-dic.xsd#ins-dic_Procent_Doli_Akczionerov_V_Uk" xlink:label="Procent_Doli_Akczionerov_V_Uk_2" xlink:title="Procent_Doli_Akczionerov_V_Uk"/>
    <link:presentationArc xlink:type="arc" xlink:arcrole="http://www.xbrl.org/2003/arcrole/parent-child" xlink:from="Sluzhebnyi_Abstract" xlink:to="Procent_Doli_Akczionerov_V_Uk_2" xlink:title="presentation: Sluzhebnyi_Abstract to Procent_Doli_Akczionerov_V_Uk" order="6.0" preferredLabel="http://www.xbrl.org/2003/role/periodEndLabel"/>
    <link:loc xlink:type="locator" xlink:href="../../../../dic/ins-dic.xsd#ins-dic_Primechanie" xlink:label="Primechanie" xlink:title="Primechanie"/>
    <link:presentationArc xlink:type="arc" xlink:arcrole="http://www.xbrl.org/2003/arcrole/parent-child" xlink:from="Sluzhebnyi_Abstract" xlink:to="Primechanie" xlink:title="presentation: Sluzhebnyi_Abstract to Primechanie" order="4.0"/>
  </link:presentationLink>
  <link:presentationLink xlink:type="extended" xlink:role="http://www.cbr.ru/xbrl/nso/ins/rep/2025-12-30/tab/sr_0420152/sr_0420152_MeneeOdinProts/2">
    <link:loc xlink:type="locator" xlink:href="../../../../dic/ins-dic.xsd#ins-dic_Sluzhebnyi_Abstract" xlink:label="Sluzhebnyi_Abstract" xlink:title="Sluzhebnyi_Abstract"/>
    <link:loc xlink:type="locator" xlink:href="http://www.eurofiling.info/eu/fr/xbrl/ext/model.xsd#hyp" xlink:label="hyp" xlink:title="hyp"/>
    <link:presentationArc xlink:type="arc" xlink:arcrole="http://www.xbrl.org/2003/arcrole/parent-child" xlink:from="Sluzhebnyi_Abstract" xlink:to="hyp" xlink:title="presentation: Sluzhebnyi_Abstract to hyp" order="1.0" xbrldt:contextElement="scenario" xbrldt:closed="true"/>
    <link:loc xlink:type="locator" xlink:href="../../../../../../udr/dim/dim-int.xsd#dim-int_Tip_Akczionerov_Axis" xlink:label="Tip_Akczionerov_Axis" xlink:title="Tip_Akczionerov_Axis"/>
    <link:presentationArc xlink:type="arc" xlink:arcrole="http://www.xbrl.org/2003/arcrole/parent-child" xlink:from="hyp" xlink:to="Tip_Akczionerov_Axis" xlink:title="presentation: hyp to Tip_Akczionerov_Axis" order="1.0"/>
    <link:loc xlink:type="locator" xlink:href="../../../../../../udr/dom/mem-int.xsd#mem-int_Rezidenty_FlMember" xlink:label="Rezidenty_FlMember" xlink:title="Rezidenty_FlMember"/>
    <link:presentationArc xlink:type="arc" xlink:arcrole="http://www.xbrl.org/2003/arcrole/parent-child" xlink:from="Tip_Akczionerov_Axis" xlink:to="Rezidenty_FlMember" xlink:title="presentation: Tip_Akczionerov_Axis to Rezidenty_FlMember" order="1.0"/>
    <link:loc xlink:type="locator" xlink:href="../../../../../../udr/dom/mem-int.xsd#mem-int_Nerezidenty_YulMember" xlink:label="Nerezidenty_YulMember" xlink:title="Nerezidenty_YulMember"/>
    <link:presentationArc xlink:type="arc" xlink:arcrole="http://www.xbrl.org/2003/arcrole/parent-child" xlink:from="Tip_Akczionerov_Axis" xlink:to="Nerezidenty_YulMember" xlink:title="presentation: Tip_Akczionerov_Axis to Nerezidenty_YulMember" order="2.0"/>
    <link:loc xlink:type="locator" xlink:href="../../../../../../udr/dom/mem-int.xsd#mem-int_Nerezidenty_FlMember" xlink:label="Nerezidenty_FlMember" xlink:title="Nerezidenty_FlMember"/>
    <link:presentationArc xlink:type="arc" xlink:arcrole="http://www.xbrl.org/2003/arcrole/parent-child" xlink:from="Tip_Akczionerov_Axis" xlink:to="Nerezidenty_FlMember" xlink:title="presentation: Tip_Akczionerov_Axis to Nerezidenty_FlMember" order="3.0"/>
    <link:loc xlink:type="locator" xlink:href="../../../../../../udr/dim/dim-int.xsd#dim-int_Tip_KontragentaAxis" xlink:label="Tip_KontragentaAxis" xlink:title="Tip_KontragentaAxis"/>
    <link:presentationArc xlink:type="arc" xlink:arcrole="http://www.xbrl.org/2003/arcrole/parent-child" xlink:from="hyp" xlink:to="Tip_KontragentaAxis" xlink:title="presentation: hyp to Tip_KontragentaAxis" order="2.0"/>
    <link:loc xlink:type="locator" xlink:href="../../../../../../udr/dom/mem-int.xsd#mem-int_AkczUchSovDolyaUkMeneeOdProtsMember" xlink:label="AkczUchSovDolyaUkMeneeOdProtsMember" xlink:title="AkczUchSovDolyaUkMeneeOdProtsMember"/>
    <link:presentationArc xlink:type="arc" xlink:arcrole="http://www.xbrl.org/2003/arcrole/parent-child" xlink:from="Tip_KontragentaAxis" xlink:to="AkczUchSovDolyaUkMeneeOdProtsMember" xlink:title="presentation: Tip_KontragentaAxis to AkczUchSovDolyaUkMeneeOdProtsMember" order="1.0"/>
    <link:loc xlink:type="locator" xlink:href="../../../../dic/ins-dic.xsd#ins-dic_Summa_Doli_Akczionerov_V_Uk" xlink:label="Summa_Doli_Akczionerov_V_Uk" xlink:title="Summa_Doli_Akczionerov_V_Uk"/>
    <link:presentationArc xlink:type="arc" xlink:arcrole="http://www.xbrl.org/2003/arcrole/parent-child" xlink:from="Sluzhebnyi_Abstract" xlink:to="Summa_Doli_Akczionerov_V_Uk" xlink:title="presentation: Sluzhebnyi_Abstract to Summa_Doli_Akczionerov_V_Uk" order="2.0" preferredLabel="http://www.xbrl.org/2003/role/periodStartLabel"/>
    <link:loc xlink:type="locator" xlink:href="../../../../dic/ins-dic.xsd#ins-dic_Summa_Doli_Akczionerov_V_Uk" xlink:label="Summa_Doli_Akczionerov_V_Uk_2" xlink:title="Summa_Doli_Akczionerov_V_Uk"/>
    <link:presentationArc xlink:type="arc" xlink:arcrole="http://www.xbrl.org/2003/arcrole/parent-child" xlink:from="Sluzhebnyi_Abstract" xlink:to="Summa_Doli_Akczionerov_V_Uk_2" xlink:title="presentation: Sluzhebnyi_Abstract to Summa_Doli_Akczionerov_V_Uk" order="5.0" preferredLabel="http://www.xbrl.org/2003/role/periodEndLabel"/>
    <link:loc xlink:type="locator" xlink:href="../../../../dic/ins-dic.xsd#ins-dic_Procent_Doli_Akczionerov_V_Uk" xlink:label="Procent_Doli_Akczionerov_V_Uk" xlink:title="Procent_Doli_Akczionerov_V_Uk"/>
    <link:presentationArc xlink:type="arc" xlink:arcrole="http://www.xbrl.org/2003/arcrole/parent-child" xlink:from="Sluzhebnyi_Abstract" xlink:to="Procent_Doli_Akczionerov_V_Uk" xlink:title="presentation: Sluzhebnyi_Abstract to Procent_Doli_Akczionerov_V_Uk" order="3.0" preferredLabel="http://www.xbrl.org/2003/role/periodStartLabel"/>
    <link:loc xlink:type="locator" xlink:href="../../../../dic/ins-dic.xsd#ins-dic_Procent_Doli_Akczionerov_V_Uk" xlink:label="Procent_Doli_Akczionerov_V_Uk_2" xlink:title="Procent_Doli_Akczionerov_V_Uk"/>
    <link:presentationArc xlink:type="arc" xlink:arcrole="http://www.xbrl.org/2003/arcrole/parent-child" xlink:from="Sluzhebnyi_Abstract" xlink:to="Procent_Doli_Akczionerov_V_Uk_2" xlink:title="presentation: Sluzhebnyi_Abstract to Procent_Doli_Akczionerov_V_Uk" order="6.0" preferredLabel="http://www.xbrl.org/2003/role/periodEndLabel"/>
    <link:loc xlink:type="locator" xlink:href="../../../../dic/ins-dic.xsd#ins-dic_Primechanie" xlink:label="Primechanie" xlink:title="Primechanie"/>
    <link:presentationArc xlink:type="arc" xlink:arcrole="http://www.xbrl.org/2003/arcrole/parent-child" xlink:from="Sluzhebnyi_Abstract" xlink:to="Primechanie" xlink:title="presentation: Sluzhebnyi_Abstract to Primechanie" order="4.0"/>
  </link:presentationLink>
  <link:presentationLink xlink:type="extended" xlink:role="http://www.cbr.ru/xbrl/nso/ins/rep/2025-12-30/tab/sr_0420152/sr_0420152_R1/1">
    <link:loc xlink:type="locator" xlink:href="http://www.eurofiling.info/eu/fr/xbrl/ext/model.xsd#hyp" xlink:label="hyp" xlink:title="hyp"/>
    <link:loc xlink:type="locator" xlink:href="../../../../../../udr/dim/dim-int.xsd#dim-int_Tip_Akczionerov_Axis" xlink:label="Tip_Akczionerov_Axis" xlink:title="Tip_Akczionerov_Axis"/>
    <link:presentationArc xlink:type="arc" xlink:arcrole="http://www.xbrl.org/2003/arcrole/parent-child" xlink:from="hyp" xlink:to="Tip_Akczionerov_Axis" xlink:title="presentation: hyp to Tip_Akczionerov_Axis" order="2.0"/>
    <link:loc xlink:type="locator" xlink:href="../../../../../../udr/dom/mem-int.xsd#mem-int_Rezidenty_YulMember" xlink:label="Rezidenty_YulMember" xlink:title="Rezidenty_YulMember"/>
    <link:presentationArc xlink:type="arc" xlink:arcrole="http://www.xbrl.org/2003/arcrole/parent-child" xlink:from="Tip_Akczionerov_Axis" xlink:to="Rezidenty_YulMember" xlink:title="presentation: Tip_Akczionerov_Axis to Rezidenty_YulMember" order="1.0"/>
    <link:loc xlink:type="locator" xlink:href="../../../../../../udr/dom/mem-int.xsd#mem-int_Rezidenty_FlMember" xlink:label="Rezidenty_FlMember" xlink:title="Rezidenty_FlMember"/>
    <link:presentationArc xlink:type="arc" xlink:arcrole="http://www.xbrl.org/2003/arcrole/parent-child" xlink:from="Tip_Akczionerov_Axis" xlink:to="Rezidenty_FlMember" xlink:title="presentation: Tip_Akczionerov_Axis to Rezidenty_FlMember" order="2.0"/>
    <link:loc xlink:type="locator" xlink:href="../../../../../../udr/dom/mem-int.xsd#mem-int_Nerezidenty_YulMember" xlink:label="Nerezidenty_YulMember" xlink:title="Nerezidenty_YulMember"/>
    <link:presentationArc xlink:type="arc" xlink:arcrole="http://www.xbrl.org/2003/arcrole/parent-child" xlink:from="Tip_Akczionerov_Axis" xlink:to="Nerezidenty_YulMember" xlink:title="presentation: Tip_Akczionerov_Axis to Nerezidenty_YulMember" order="3.0"/>
    <link:loc xlink:type="locator" xlink:href="../../../../../../udr/dom/mem-int.xsd#mem-int_Nerezidenty_FlMember" xlink:label="Nerezidenty_FlMember" xlink:title="Nerezidenty_FlMember"/>
    <link:presentationArc xlink:type="arc" xlink:arcrole="http://www.xbrl.org/2003/arcrole/parent-child" xlink:from="Tip_Akczionerov_Axis" xlink:to="Nerezidenty_FlMember" xlink:title="presentation: Tip_Akczionerov_Axis to Nerezidenty_FlMember" order="4.0"/>
    <link:loc xlink:type="locator" xlink:href="../../../../../../udr/dim/dim-int.xsd#dim-int_ID_akczioneraTaxis" xlink:label="ID_akczioneraTaxis" xlink:title="ID_akczioneraTaxis"/>
    <link:presentationArc xlink:type="arc" xlink:arcrole="http://www.xbrl.org/2003/arcrole/parent-child" xlink:from="hyp" xlink:to="ID_akczioneraTaxis" xlink:title="presentation: hyp to ID_akczioneraTaxis" order="1.0"/>
    <link:loc xlink:type="locator" xlink:href="../../../../dic/ins-dic.xsd#ins-dic_Podr1_1Rezidenty-Ylneyavldochobpootnukinostrinvest_Abstract" xlink:label="Podr1_1Rezidenty-Ylneyavldochobpootnukinostrinvest_Abstract" xlink:title="Podr1_1Rezidenty-Ylneyavldochobpootnukinostrinvest_Abstract"/>
    <link:presentationArc xlink:type="arc" xlink:arcrole="http://www.xbrl.org/2003/arcrole/parent-child" xlink:from="Podr1_1Rezidenty-Ylneyavldochobpootnukinostrinvest_Abstract" xlink:to="hyp" xlink:title="presentation: Podr1_1Rezidenty-Ylneyavldochobpootnukinostrinvest_Abstract to hyp" order="1.0" xbrldt:closed="true" xbrldt:contextElement="scenario"/>
    <link:loc xlink:type="locator" xlink:href="../../../../dic/ins-dic.xsd#ins-dic_Summa_Doli_Akczionerov_V_Uk" xlink:label="Summa_Doli_Akczionerov_V_Uk" xlink:title="Summa_Doli_Akczionerov_V_Uk"/>
    <link:presentationArc xlink:type="arc" xlink:arcrole="http://www.xbrl.org/2003/arcrole/parent-child" xlink:from="Podr1_1Rezidenty-Ylneyavldochobpootnukinostrinvest_Abstract" xlink:to="Summa_Doli_Akczionerov_V_Uk" xlink:title="presentation: Podr1_1Rezidenty-Ylneyavldochobpootnukinostrinvest_Abstract to Summa_Doli_Akczionerov_V_Uk" order="2.0" preferredLabel="http://www.xbrl.org/2003/role/periodStartLabel"/>
    <link:loc xlink:type="locator" xlink:href="../../../../dic/ins-dic.xsd#ins-dic_Summa_Doli_Akczionerov_V_Uk" xlink:label="Summa_Doli_Akczionerov_V_Uk_2" xlink:title="Summa_Doli_Akczionerov_V_Uk"/>
    <link:presentationArc xlink:type="arc" xlink:arcrole="http://www.xbrl.org/2003/arcrole/parent-child" xlink:from="Podr1_1Rezidenty-Ylneyavldochobpootnukinostrinvest_Abstract" xlink:to="Summa_Doli_Akczionerov_V_Uk_2" xlink:title="presentation: Podr1_1Rezidenty-Ylneyavldochobpootnukinostrinvest_Abstract to Summa_Doli_Akczionerov_V_Uk" order="5.0" preferredLabel="http://www.xbrl.org/2003/role/periodEndLabel"/>
    <link:loc xlink:type="locator" xlink:href="../../../../dic/ins-dic.xsd#ins-dic_Procent_Doli_Akczionerov_V_Uk" xlink:label="Procent_Doli_Akczionerov_V_Uk" xlink:title="Procent_Doli_Akczionerov_V_Uk"/>
    <link:presentationArc xlink:type="arc" xlink:arcrole="http://www.xbrl.org/2003/arcrole/parent-child" xlink:from="Podr1_1Rezidenty-Ylneyavldochobpootnukinostrinvest_Abstract" xlink:to="Procent_Doli_Akczionerov_V_Uk" xlink:title="presentation: Podr1_1Rezidenty-Ylneyavldochobpootnukinostrinvest_Abstract to Procent_Doli_Akczionerov_V_Uk" order="3.0" preferredLabel="http://www.xbrl.org/2003/role/periodStartLabel"/>
    <link:loc xlink:type="locator" xlink:href="../../../../dic/ins-dic.xsd#ins-dic_Procent_Doli_Akczionerov_V_Uk" xlink:label="Procent_Doli_Akczionerov_V_Uk_2" xlink:title="Procent_Doli_Akczionerov_V_Uk"/>
    <link:presentationArc xlink:type="arc" xlink:arcrole="http://www.xbrl.org/2003/arcrole/parent-child" xlink:from="Podr1_1Rezidenty-Ylneyavldochobpootnukinostrinvest_Abstract" xlink:to="Procent_Doli_Akczionerov_V_Uk_2" xlink:title="presentation: Podr1_1Rezidenty-Ylneyavldochobpootnukinostrinvest_Abstract to Procent_Doli_Akczionerov_V_Uk" order="6.0" preferredLabel="http://www.xbrl.org/2003/role/periodEndLabel"/>
    <link:loc xlink:type="locator" xlink:href="../../../../dic/ins-dic.xsd#ins-dic_Primechanie" xlink:label="Primechanie" xlink:title="Primechanie"/>
    <link:presentationArc xlink:type="arc" xlink:arcrole="http://www.xbrl.org/2003/arcrole/parent-child" xlink:from="Podr1_1Rezidenty-Ylneyavldochobpootnukinostrinvest_Abstract" xlink:to="Primechanie" xlink:title="presentation: Podr1_1Rezidenty-Ylneyavldochobpootnukinostrinvest_Abstract to Primechanie" order="4.0"/>
  </link:presentationLink>
  <link:presentationLink xlink:type="extended" xlink:role="http://www.cbr.ru/xbrl/nso/ins/rep/2025-12-30/tab/sr_0420152/sr_0420152_R1Spr">
    <link:loc xlink:type="locator" xlink:href="../../../../dic/ins-dic.xsd#ins-dic_SpravkaobustavnomkapitaleAbstract" xlink:label="SpravkaobustavnomkapitaleAbstract" xlink:title="SpravkaobustavnomkapitaleAbstract"/>
    <link:loc xlink:type="locator" xlink:href="http://www.eurofiling.info/eu/fr/xbrl/ext/model.xsd#hyp" xlink:label="hyp" xlink:title="hyp"/>
    <link:presentationArc xlink:type="arc" xlink:arcrole="http://www.xbrl.org/2003/arcrole/parent-child" xlink:from="SpravkaobustavnomkapitaleAbstract" xlink:to="hyp" xlink:title="presentation: SpravkaobustavnomkapitaleAbstract to hyp" order="1.0" xbrldt:closed="true" xbrldt:contextElement="scenario"/>
    <link:loc xlink:type="locator" xlink:href="../../../../dic/ins-dic.xsd#ins-dic_Uk_Vsego" xlink:label="Uk_Vsego" xlink:title="Uk_Vsego"/>
    <link:presentationArc xlink:type="arc" xlink:arcrole="http://www.xbrl.org/2003/arcrole/parent-child" xlink:from="SpravkaobustavnomkapitaleAbstract" xlink:to="Uk_Vsego" xlink:title="presentation: SpravkaobustavnomkapitaleAbstract to Uk_Vsego" order="2.0" preferredLabel="http://www.xbrl.org/2003/role/periodStartLabel"/>
    <link:loc xlink:type="locator" xlink:href="../../../../dic/ins-dic.xsd#ins-dic_Uk_Vsego" xlink:label="Uk_Vsego_2" xlink:title="Uk_Vsego"/>
    <link:presentationArc xlink:type="arc" xlink:arcrole="http://www.xbrl.org/2003/arcrole/parent-child" xlink:from="SpravkaobustavnomkapitaleAbstract" xlink:to="Uk_Vsego_2" xlink:title="presentation: SpravkaobustavnomkapitaleAbstract to Uk_Vsego" order="5.0" preferredLabel="http://www.xbrl.org/2003/role/periodEndLabel"/>
    <link:loc xlink:type="locator" xlink:href="../../../../dic/ins-dic.xsd#ins-dic_Sobstvakcziivykupakczionerov_Nominstoim" xlink:label="Sobstvakcziivykupakczionerov_Nominstoim" xlink:title="Sobstvakcziivykupakczionerov_Nominstoim"/>
    <link:presentationArc xlink:type="arc" xlink:arcrole="http://www.xbrl.org/2003/arcrole/parent-child" xlink:from="SpravkaobustavnomkapitaleAbstract" xlink:to="Sobstvakcziivykupakczionerov_Nominstoim" xlink:title="presentation: SpravkaobustavnomkapitaleAbstract to Sobstvakcziivykupakczionerov_Nominstoim" order="3.0" preferredLabel="http://www.xbrl.org/2003/role/periodStartLabel"/>
    <link:loc xlink:type="locator" xlink:href="../../../../dic/ins-dic.xsd#ins-dic_Sobstvakcziivykupakczionerov_Nominstoim" xlink:label="Sobstvakcziivykupakczionerov_Nominstoim_2" xlink:title="Sobstvakcziivykupakczionerov_Nominstoim"/>
    <link:presentationArc xlink:type="arc" xlink:arcrole="http://www.xbrl.org/2003/arcrole/parent-child" xlink:from="SpravkaobustavnomkapitaleAbstract" xlink:to="Sobstvakcziivykupakczionerov_Nominstoim_2" xlink:title="presentation: SpravkaobustavnomkapitaleAbstract to Sobstvakcziivykupakczionerov_Nominstoim" order="6.0" preferredLabel="http://www.xbrl.org/2003/role/periodEndLabel"/>
    <link:loc xlink:type="locator" xlink:href="../../../../dic/ins-dic.xsd#ins-dic_Dz_Akczionerov_Po_Vznosam_V_Uk_Ostatok" xlink:label="Dz_Akczionerov_Po_Vznosam_V_Uk_Ostatok" xlink:title="Dz_Akczionerov_Po_Vznosam_V_Uk_Ostatok"/>
    <link:presentationArc xlink:type="arc" xlink:arcrole="http://www.xbrl.org/2003/arcrole/parent-child" xlink:from="SpravkaobustavnomkapitaleAbstract" xlink:to="Dz_Akczionerov_Po_Vznosam_V_Uk_Ostatok" xlink:title="presentation: SpravkaobustavnomkapitaleAbstract to Dz_Akczionerov_Po_Vznosam_V_Uk_Ostatok" order="4.0" preferredLabel="http://www.xbrl.org/2003/role/periodStartLabel"/>
    <link:loc xlink:type="locator" xlink:href="../../../../dic/ins-dic.xsd#ins-dic_Dz_Akczionerov_Po_Vznosam_V_Uk_Ostatok" xlink:label="Dz_Akczionerov_Po_Vznosam_V_Uk_Ostatok_2" xlink:title="Dz_Akczionerov_Po_Vznosam_V_Uk_Ostatok"/>
    <link:presentationArc xlink:type="arc" xlink:arcrole="http://www.xbrl.org/2003/arcrole/parent-child" xlink:from="SpravkaobustavnomkapitaleAbstract" xlink:to="Dz_Akczionerov_Po_Vznosam_V_Uk_Ostatok_2" xlink:title="presentation: SpravkaobustavnomkapitaleAbstract to Dz_Akczionerov_Po_Vznosam_V_Uk_Ostatok" order="7.0" preferredLabel="http://www.xbrl.org/2003/role/periodEndLabel"/>
  </link:presentationLink>
</link:linkbase>
